tests/__init__.py
tests/benchmark.py
tests/complexity_measures_intuition.py
tests/performance_tests_acf.py
tests/test_calc_features.py
tests/test_dataset_loaders.py
tests/test_features.py
tests/test_features_settings.py
tests/test_signal_processing.py
tests/datasets/__init__.py
tests/datasets/empirical1000_dataset.py
tests/tests_tools/__init__.py
tests/tests_tools/test_personal_features.py
tsfel/__init__.py
tsfel/constants.py
tsfel/datasets/__init__.py
tsfel/datasets/_single_problem_loaders.py
tsfel/feature_extraction/__init__.py
tsfel/feature_extraction/calc_features.py
tsfel/feature_extraction/features.json
tsfel/feature_extraction/features.py
tsfel/feature_extraction/features_settings.py
tsfel/feature_extraction/features_utils.py
tsfel/utils/__init__.py
tsfel/utils/add_personal_features.py
tsfel/utils/calculate_complexity.py
tsfel/utils/progress_bar.py
tsfel/utils/signal_processing.py
tsfel-0.2.0.dist-info/AUTHORS.rst
tsfel-0.2.0.dist-info/LICENSE.txt
tsfel-0.2.0.dist-info/METADATA
tsfel-0.2.0.dist-info/WHEEL
tsfel-0.2.0.dist-info/top_level.txt
tsfel-0.2.0.dist-info/RECORD
