Metadata-Version: 2.1
Name: tsfel
Version: 0.2.0
Summary: Library for time series feature extraction
Home-page: https://github.com/fraunhoferportugal/tsfel/
Author: Fraunhofer Portugal
Classifier: Programming Language :: Python :: 3
Classifier: License :: OSI Approved :: BSD License
Classifier: Operating System :: OS Independent
License-File: LICENSE.txt
License-File: AUTHORS.rst
Requires-Dist: ipython>=7.4.0
Requires-Dist: numpy>=1.18.5
Requires-Dist: pandas>=1.5.3
Requires-Dist: PyWavelets>=1.4.1
Requires-Dist: requests>=2.31.0
Requires-Dist: scikit-learn>=0.21.3
Requires-Dist: scipy>=1.7.3
Requires-Dist: setuptools>=47.1.1
Requires-Dist: statsmodels>=0.12.0
Provides-Extra: docs
Requires-Dist: Sphinx>=7.2.6; extra == "docs"
Requires-Dist: sphinx-rtd-theme>=1.3.0; extra == "docs"
